{"items":[{"site_id":"tophub","site_name":"TopHub","source":"快手 · 实时热榜","title":"周六福金手镯退款争议","url":"https://index.e.kuaishou.com/rank/hotDetail?keyword=%E5%91%A8%E5%85%AD%E7%A6%8F%E9%87%91%E6%89%8B%E9%95%AF%E9%80%80%E6%AC%BE%E4%BA%89%E8%AE%AE&rankType=1","published_at":null,"first_seen_at":"2026-03-14T02:28:43.039445Z","title_en":null,"title_zh":"周六福金手镯退款争议"},{"site_id":"tophub","site_name":"TopHub","source":"快手 · 实时热榜","title":"巴西前总统住进ICU","url":"https://index.e.kuaishou.com/rank/hotDetail?keyword=%E5%B7%B4%E8%A5%BF%E5%89%8D%E6%80%BB%E7%BB%9F%E4%BD%8F%E8%BF%9BICU&rankType=1","published_at":null,"first_seen_at":"2026-03-14T02:28:43.039445Z","title_en":null,"title_zh":"巴西前总统住进ICU"},{"site_id":"tophub","site_name":"TopHub","source":"快手 · 实时热榜","title":"吉林小孩哥求小姨低调接放学","url":"https://index.e.kuaishou.com/rank/hotDetail?keyword=%E5%90%89%E6%9E%97%E5%B0%8F%E5%AD%A9%E5%93%A5%E6%B1%82%E5%B0%8F%E5%A7%A8%E4%BD%8E%E8%B0%83%E6%8E%A5%E6%94%BE%E5%AD%A6&rankType=1","published_at":null,"first_seen_at":"2026-03-14T02:28:43.039445Z","title_en":null,"title_zh":"吉林小孩哥求小姨低调接放学"},{"site_id":"tophub","site_name":"TopHub","source":"快手 · 实时热榜","title":"龙岩理发店暗售野生动物","url":"https://index.e.kuaishou.com/rank/hotDetail?keyword=%E9%BE%99%E5%B2%A9%E7%90%86%E5%8F%91%E5%BA%97%E6%9A%97%E5%94%AE%E9%87%8E%E7%94%9F%E5%8A%A8%E7%89%A9&rankType=1","published_at":null,"first_seen_at":"2026-03-14T02:28:43.039445Z","title_en":null,"title_zh":"龙岩理发店暗售野生动物"},{"site_id":"tophub","site_name":"TopHub","source":"快手 · 实时热榜","title":"赤峰销毁10万元假酒","url":"https://index.e.kuaishou.com/rank/hotDetail?keyword=%E8%B5%A4%E5%B3%B0%E9%94%80%E6%AF%8110%E4%B8%87%E5%85%83%E5%81%87%E9%85%92&rankType=1","published_at":null,"first_seen_at":"2026-03-14T02:28:43.039445Z","title_en":null,"title_zh":"赤峰销毁10万元假酒"},{"site_id":"tophub","site_name":"TopHub","source":"快手 · 实时热榜","title":"房子卖了30万佣金要按100万收","url":"https://index.e.kuaishou.com/rank/hotDetail?keyword=%E6%88%BF%E5%AD%90%E5%8D%96%E4%BA%8630%E4%B8%87%E4%BD%A3%E9%87%91%E8%A6%81%E6%8C%89100%E4%B8%87%E6%94%B6&rankType=1","published_at":null,"first_seen_at":"2026-03-14T02:28:43.039445Z","title_en":null,"title_zh":"房子卖了30万佣金要按100万收"},{"site_id":"tophub","site_name":"TopHub","source":"虎扑社区 · 步行街热帖","title":"周末愉快","url":"https://bbs.hupu.com/637889706.html","published_at":null,"first_seen_at":"2026-03-14T02:28:43.039445Z","title_en":null,"title_zh":"周末愉快"},{"site_id":"tophub","site_name":"TopHub","source":"淘宝 · TOP100人气榜","title":"【国企甄选】秋慕思田汉江大米10斤 原价¥44.9 券后¥26.9","url":"https://tophub.today/link?domain=taobao.com&url=https%3A%2F%2Fremai.today%2Flink%2F1%2FGK8B00B3f8tYmajVAWRiYxOhQtJ-OqGjQoAu03vOyjrRu8Z","published_at":null,"first_seen_at":"2026-03-14T02:28:43.039445Z","title_en":null,"title_zh":"【国企甄选】秋慕思田汉江大米10斤 原价¥44.9 券后¥26.9"},{"site_id":"tophub","site_name":"TopHub","source":"虎扑社区 · NBA论坛热帖","title":"[流言板]杰伦-格林连续单打干拔三分投进，三分13中8已砍下34分","url":"https://bbs.hupu.com/637890010.html","published_at":null,"first_seen_at":"2026-03-14T02:28:43.039445Z","title_en":null,"title_zh":"[流言板]杰伦-格林连续单打干拔三分投进，三分13中8已砍下34分"},{"site_id":"tophub","site_name":"TopHub","source":"虎扑社区 · NBA论坛热帖","title":"[流言板]船记：科林斯已经参加五对五的队内训练，颈部伤势恢复良好","url":"https://bbs.hupu.com/637889478.html","published_at":null,"first_seen_at":"2026-03-14T02:28:43.039445Z","title_en":null,"title_zh":"[流言板]船记：科林斯已经参加五对五的队内训练，颈部伤势恢复良好"},{"site_id":"tophub","site_name":"TopHub","source":"虎扑社区 · NBA论坛热帖","title":"[流言板]弗拉格是本赛季唯一得分篮板和助攻全部领跑全队的新秀","url":"https://bbs.hupu.com/637889548.html","published_at":null,"first_seen_at":"2026-03-14T02:28:43.039445Z","title_en":null,"title_zh":"[流言板]弗拉格是本赛季唯一得分篮板和助攻全部领跑全队的新秀"},{"site_id":"tophub","site_name":"TopHub","source":"虎扑社区 · NBA论坛热帖","title":"巅峰杜兰特去19赛季，未必输","url":"https://bbs.hupu.com/637889055.html","published_at":null,"first_seen_at":"2026-03-14T02:28:43.039445Z","title_en":null,"title_zh":"巅峰杜兰特去19赛季，未必输"},{"site_id":"tophub","site_name":"TopHub","source":"虎扑社区 · NBA论坛热帖","title":"[流言板]关键时刻杰伦-格林被背后封盖，巴雷特快攻暴扣杀死比赛","url":"https://bbs.hupu.com/637890486.html","published_at":null,"first_seen_at":"2026-03-14T02:28:43.039445Z","title_en":null,"title_zh":"[流言板]关键时刻杰伦-格林被背后封盖，巴雷特快攻暴扣杀死比赛"},{"site_id":"tophub","site_name":"TopHub","source":"虎扑社区 · NBA论坛热帖","title":"[流言板]哈登全场11投6中，三分7中3得到17分7篮板7助攻1抢断","url":"https://bbs.hupu.com/637890341.html","published_at":null,"first_seen_at":"2026-03-14T02:28:43.039445Z","title_en":null,"title_zh":"[流言板]哈登全场11投6中，三分7中3得到17分7篮板7助攻1抢断"},{"site_id":"tophub","site_name":"TopHub","source":"淘宝 ‧ 天猫 · 热销总榜","title":"七度空间日夜用任选10赠2 原价¥200.9 券后¥33.9","url":"https://tophub.today/link?domain=taobao.com&url=https%3A%2F%2Fremai.today%2Flink%2F1%2FM84grjVcKtX4GeAY2WTV87SQt5-VrGvymkIkOOKkwM5Cn","published_at":null,"first_seen_at":"2026-03-14T02:28:43.039445Z","title_en":null,"title_zh":"七度空间日夜用任选10赠2 原价¥200.9 券后¥33.9"},{"site_id":"tophub","site_name":"TopHub","source":"淘宝 · TOP100人气榜","title":"海天薄盐生抽500ml*2瓶 原价¥10.9 券后¥9.9","url":"https://tophub.today/link?domain=taobao.com&url=https%3A%2F%2Fremai.today%2Flink%2F1%2FP5jdg4Wc3t6rMXeN0NtvmRuPt6-gPGqkKxUAX9dRZ97SG2","published_at":null,"first_seen_at":"2026-03-14T02:28:43.039445Z","title_en":null,"title_zh":"海天薄盐生抽500ml*2瓶 原价¥10.9 券后¥9.9"},{"site_id":"tophub","site_name":"TopHub","source":"淘宝 ‧ 天猫 · 热销总榜","title":"选3只！晚芽日记无氟儿童牙膏 原价¥14.9 券后¥9.9","url":"https://tophub.today/link?domain=taobao.com&url=https%3A%2F%2Fremai.today%2Flink%2F1%2FWqe7ProPHot2qnyarOoiaYmhQtW-YJGeOZNHBRRNyg0VFa","published_at":null,"first_seen_at":"2026-03-14T02:28:43.039445Z","title_en":null,"title_zh":"选3只！晚芽日记无氟儿童牙膏 原价¥14.9 券后¥9.9"},{"site_id":"tophub","site_name":"TopHub","source":"淘宝 ‧ 天猫 · 热销总榜","title":"国货老牌子驱蚊嘎嘎牛！力圣蚊香液3液一器 原价¥22.9 券后¥12.9","url":"https://tophub.today/link?domain=taobao.com&url=https%3A%2F%2Fremai.today%2Flink%2F1%2FGKaqjbD6s8tYmaXPJKniYx2FQtJ-jGwQkK5TXr9eAmeYHz6","published_at":null,"first_seen_at":"2026-03-14T02:28:43.039445Z","title_en":null,"title_zh":"国货老牌子驱蚊嘎嘎牛！力圣蚊香液3液一器 原价¥22.9 券后¥12.9"},{"site_id":"tophub","site_name":"TopHub","source":"淘宝 · TOP100人气榜","title":"babycare恐龙蛋儿童防晒乳 原价¥94 券后¥24","url":"https://tophub.today/link?domain=taobao.com&url=https%3A%2F%2Fremai.today%2Flink%2F1%2F4VNkQQGJHgtNgoRA85GswgxiNtg-ANgJ0akHKomd97yKTDx","published_at":null,"first_seen_at":"2026-03-14T02:28:43.039445Z","title_en":null,"title_zh":"babycare恐龙蛋儿童防晒乳 原价¥94 券后¥24"},{"site_id":"tophub","site_name":"TopHub","source":"淘宝 ‧ 天猫 · 热销总榜","title":"【已公开】】newpage一页儿童蛋黄油面霜 原价¥59.8 券后¥24.8","url":"https://tophub.today/link?domain=taobao.com&url=https%3A%2F%2Fremai.today%2Flink%2F1%2F9DJOXJKIBtOqMPNrozT20niQt6-ANgJ0akHKZVPpM5buYZ","published_at":null,"first_seen_at":"2026-03-14T02:28:43.039445Z","title_en":null,"title_zh":"【已公开】】newpage一页儿童蛋黄油面霜 原价¥59.8 券后¥24.8"},{"site_id":"tophub","site_name":"TopHub","source":"淘宝 ‧ 天猫 · 热销总榜","title":"唐狮集团DESSO男女款短袖 原价¥239.7 券后¥39.7","url":"https://tophub.today/link?domain=taobao.com&url=https%3A%2F%2Fremai.today%2Flink%2F1%2FgJvd9pRf3t2AZ4ayznuo3NIatr-gPGqkKxUA0rVyo9GCoY","published_at":null,"first_seen_at":"2026-03-14T02:28:43.039445Z","title_en":null,"title_zh":"唐狮集团DESSO男女款短袖 原价¥239.7 券后¥39.7"},{"site_id":"tophub","site_name":"TopHub","source":"淘宝 ‧ 天猫 · 热销总榜","title":"高洁丝全周期全系列任选 原价¥55 券后¥39","url":"https://tophub.today/link?domain=taobao.com&url=https%3A%2F%2Fremai.today%2Flink%2F1%2F7AB0JrRU4t5OmwwR7YFn3YTMtb-6RmxkGoIy8WrKgbbfKg","published_at":null,"first_seen_at":"2026-03-14T02:28:43.039445Z","title_en":null,"title_zh":"高洁丝全周期全系列任选 原价¥55 券后¥39"},{"site_id":"tophub","site_name":"TopHub","source":"淘宝 ‧ 天猫 · 热销总榜","title":"双汇简颂低GI鸡肉午餐肉 原价¥14.04 券后¥9.04","url":"https://tophub.today/link?domain=taobao.com&url=https%3A%2F%2Fremai.today%2Flink%2F1%2FdOPz582UZt3Z2GJj6vfj4dFet3-aRG5QXwIdJoQVWO8fz","published_at":null,"first_seen_at":"2026-03-14T02:28:43.039445Z","title_en":null,"title_zh":"双汇简颂低GI鸡肉午餐肉 原价¥14.04 券后¥9.04"},{"site_id":"tophub","site_name":"TopHub","source":"淘宝 ‧ 天猫 · 热销总榜","title":"【20款可选】牛奶绒四件套双面珊瑚绒被套 原价¥638 券后¥138","url":"https://tophub.today/link?domain=taobao.com&url=https%3A%2F%2Fremai.today%2Flink%2F1%2FpBdo0a7vHxt63apGOrBCe2aiptm-k3edXK7sRbVDgAn8C5a","published_at":null,"first_seen_at":"2026-03-14T02:28:43.039445Z","title_en":null,"title_zh":"【20款可选】牛奶绒四件套双面珊瑚绒被套 原价¥638 券后¥138"},{"site_id":"tophub","site_name":"TopHub","source":"淘宝 · TOP100人气榜","title":"【加赠1袋】臭宝柳州螺蛳粉300g*3+258g*3袋 原价¥49.9 券后¥46.9","url":"https://tophub.today/link?domain=taobao.com&url=https%3A%2F%2Fremai.today%2Flink%2F1%2F82vOjbyhnt9yPNNOzZUgbGibtj-YJGeOZNHj6ejpwAZCRB","published_at":null,"first_seen_at":"2026-03-14T02:28:43.039445Z","title_en":null,"title_zh":"【加赠1袋】臭宝柳州螺蛳粉300g*3+258g*3袋 原价¥49.9 券后¥46.9"},{"site_id":"tophub","site_name":"TopHub","source":"淘宝 ‧ 天猫 · 每日爆款清单","title":"【瑷尔博士】养肤防晒霜50g 原价¥79 券后¥17","url":"https://tophub.today/link?domain=taobao.com&url=https%3A%2F%2Fremai.today%2Flink%2F1%2FBVVzoZjF6t84vVk9JxipB9Urte-D3G9b6AsPy0DYGnDSn","published_at":null,"first_seen_at":"2026-03-14T02:28:43.039445Z","title_en":null,"title_zh":"【瑷尔博士】养肤防晒霜50g 原价¥79 券后¥17"},{"site_id":"tophub","site_name":"TopHub","source":"淘宝 ‧ 天猫 · 每日爆款清单","title":"婴儿专用电动鼻塞通鼻器 原价¥59 券后¥49","url":"https://tophub.today/link?domain=taobao.com&url=https%3A%2F%2Fremai.today%2Flink%2F1%2F6ozGpabi8tGyD9oyX3cw98iot3-Q0GkBmxs9jwrZJQ8uK","published_at":null,"first_seen_at":"2026-03-14T02:28:43.039445Z","title_en":null,"title_zh":"婴儿专用电动鼻塞通鼻器 原价¥59 券后¥49"},{"site_id":"tophub","site_name":"TopHub","source":"淘宝 ‧ 天猫 · 每日爆款清单","title":"贝易宝宝水杯婴儿学饮杯喝牛奶杯420ml 原价¥88 券后¥38","url":"https://tophub.today/link?domain=taobao.com&url=https%3A%2F%2Fremai.today%2Flink%2F1%2FGemvobgC8tYmQMOMJ7fYqvfQtJ-4V2A3ZgI8dQRxA4vHB","published_at":null,"first_seen_at":"2026-03-14T02:28:43.039445Z","title_en":null,"title_zh":"贝易宝宝水杯婴儿学饮杯喝牛奶杯420ml 原价¥88 券后¥38"},{"site_id":"tophub","site_name":"TopHub","source":"淘宝 ‧ 天猫 · 每日爆款清单","title":"兔头妈妈桃叶精华儿童洗发水280ml*2瓶 原价¥39.8 券后¥39.8","url":"https://tophub.today/link?domain=taobao.com&url=https%3A%2F%2Fremai.today%2Flink%2F1%2FNG5YrG9T5tGnRqWogQTxJBHRtB-Q0GkBmxsbRj0R8DDuKj","published_at":null,"first_seen_at":"2026-03-14T02:28:43.039445Z","title_en":null,"title_zh":"兔头妈妈桃叶精华儿童洗发水280ml*2瓶 原价¥39.8 券后¥39.8"},{"site_id":"tophub","site_name":"TopHub","source":"淘宝 ‧ 天猫 · 每日爆款清单","title":"Pigeon贝亲婴儿宽口径玻璃奶瓶240mlM号奶嘴 原价¥151.2 券后¥134.2","url":"https://tophub.today/link?domain=taobao.com&url=https%3A%2F%2Fremai.today%2Flink%2F1%2FMy4DZw5fKtX47nYK0bUVWxUQtA-26VpOQjCMMzpBKdmCv","published_at":null,"first_seen_at":"2026-03-14T02:28:43.039445Z","title_en":null,"title_zh":"Pigeon贝亲婴儿宽口径玻璃奶瓶240mlM号奶嘴 原价¥151.2 券后¥134.2"},{"site_id":"tophub","site_name":"TopHub","source":"淘宝 ‧ 天猫 · 每日爆款清单","title":"电动电瓶摩托车雨衣 加厚长款防暴雨大码雨披 原价¥18.7 券后¥13.7","url":"https://tophub.today/link?domain=taobao.com&url=https%3A%2F%2Fremai.today%2Flink%2F1%2FjwYKAYgs0tJq5V33mmhBbpfJte-GKGOWR8cbOyDaga7CZG","published_at":null,"first_seen_at":"2026-03-14T02:28:43.039445Z","title_en":null,"title_zh":"电动电瓶摩托车雨衣 加厚长款防暴雨大码雨披 原价¥18.7 券后¥13.7"},{"site_id":"tophub","site_name":"TopHub","source":"淘宝 ‧ 天猫 · 每日爆款清单","title":"【限5000单】粉笔文创黑羽16开草稿本 原价¥6.27 券后¥1.27","url":"https://tophub.today/link?domain=taobao.com&url=https%3A%2F%2Fremai.today%2Flink%2F1%2Fzg2pZV8ietan4KnPX5SvyKudtj-jGwQkK5TdgXg8Ax0ie","published_at":null,"first_seen_at":"2026-03-14T02:28:43.039445Z","title_en":null,"title_zh":"【限5000单】粉笔文创黑羽16开草稿本 原价¥6.27 券后¥1.27"},{"site_id":"tophub","site_name":"TopHub","source":"淘宝 ‧ 天猫 · 每日爆款清单","title":"升级版inne小金条钙镁锌 原价¥358 券后¥318","url":"https://tophub.today/link?domain=taobao.com&url=https%3A%2F%2Fremai.today%2Flink%2F1%2FYXRqDZDfptXkm2PG9KuWq4T2t6-7no8vaXHww3eoqAnf7","published_at":null,"first_seen_at":"2026-03-14T02:28:43.039445Z","title_en":null,"title_zh":"升级版inne小金条钙镁锌 原价¥358 券后¥318"},{"site_id":"tophub","site_name":"TopHub","source":"淘宝 ‧ 天猫 · 每日爆款清单","title":"万谷食美山西黄小米2斤罐装五谷杂粮 原价¥6.33 券后¥6.33","url":"https://tophub.today/link?domain=taobao.com&url=https%3A%2F%2Fremai.today%2Flink%2F1%2FBvbgbr6t6t84drMW6McpKMIrte-mPkBXe3U7Q2Z8AX7SY0","published_at":null,"first_seen_at":"2026-03-14T02:28:43.039445Z","title_en":null,"title_zh":"万谷食美山西黄小米2斤罐装五谷杂粮 原价¥6.33 券后¥6.33"},{"site_id":"tophub","site_name":"TopHub","source":"淘宝 ‧ 天猫 · 每日爆款清单","title":"理肤泉特安洁面泡沫敏感肌温和50ml*2支 原价¥50 券后¥40","url":"https://tophub.today/link?domain=taobao.com&url=https%3A%2F%2Fremai.today%2Flink%2F1%2FjaADRBNU0tJq5yz9yVFBpotJtv-26VpOQjCOJ38qOJ0uZj","published_at":null,"first_seen_at":"2026-03-14T02:28:43.039445Z","title_en":null,"title_zh":"理肤泉特安洁面泡沫敏感肌温和50ml*2支 原价¥50 券后¥40"},{"site_id":"tophub","site_name":"TopHub","source":"淘宝 ‧ 天猫 · 每日爆款清单","title":"有机金芍耳本草银耳羹冲泡即食 原价¥12.9 券后¥9.9","url":"https://tophub.today/link?domain=taobao.com&url=https%3A%2F%2Fremai.today%2Flink%2F1%2FB5pnPwdh6t84dzvVQnhpBqfrte-88DbxaKC0d5R2J3NiAb","published_at":null,"first_seen_at":"2026-03-14T02:28:43.039445Z","title_en":null,"title_zh":"有机金芍耳本草银耳羹冲泡即食 原价¥12.9 券后¥9.9"},{"site_id":"tophub","site_name":"TopHub","source":"淘宝 ‧ 天猫 · 每日爆款清单","title":"国货之光！连续三年湿厕纸第1名 原价¥17.9 券后¥17.9","url":"https://tophub.today/link?domain=taobao.com&url=https%3A%2F%2Fremai.today%2Flink%2F1%2FMPOyzgo2iKtX4GX35zKtVpeTQtA-eQGMq6ACGD8O9wR2T9q","published_at":null,"first_seen_at":"2026-03-14T02:28:43.039445Z","title_en":null,"title_zh":"国货之光！连续三年湿厕纸第1名 原价¥17.9 券后¥17.9"},{"site_id":"tophub","site_name":"TopHub","source":"微博 · 热搜榜","title":"财务离职总经理转错公账23万余元","url":"https://s.weibo.com/weibo?q=%E8%B4%A2%E5%8A%A1%E7%A6%BB%E8%81%8C%E6%80%BB%E7%BB%8F%E7%90%86%E8%BD%AC%E9%94%99%E5%85%AC%E8%B4%A623%E4%B8%87%E4%BD%99%E5%85%83","published_at":null,"first_seen_at":"2026-03-14T02:28:43.039445Z","title_en":null,"title_zh":"财务离职总经理转错公账23万余元"},{"site_id":"tophub","site_name":"TopHub","source":"微博 · 热搜榜","title":"国家网络安全通报中心通报OpenClaw风险","url":"https://s.weibo.com/weibo?q=%E5%9B%BD%E5%AE%B6%E7%BD%91%E7%BB%9C%E5%AE%89%E5%85%A8%E9%80%9A%E6%8A%A5%E4%B8%AD%E5%BF%83%E9%80%9A%E6%8A%A5OpenClaw%E9%A3%8E%E9%99%A9","published_at":null,"first_seen_at":"2026-03-14T02:28:43.039445Z","title_en":null,"title_zh":"国家网络安全通报中心通报OpenClaw风险"},{"site_id":"tophub","site_name":"TopHub","source":"微博 · 热搜榜","title":"美团外卖周末半价吃大餐","url":"https://s.weibo.com/weibo?q=%E7%BE%8E%E5%9B%A2%E5%A4%96%E5%8D%96%E5%91%A8%E6%9C%AB%E5%8D%8A%E4%BB%B7%E5%90%83%E5%A4%A7%E9%A4%90","published_at":null,"first_seen_at":"2026-03-14T02:28:43.039445Z","title_en":null,"title_zh":"美团外卖周末半价吃大餐"},{"site_id":"tophub","site_name":"TopHub","source":"微博 · 热搜榜","title":"如果一个人的朋友圈特别正常","url":"https://s.weibo.com/weibo?q=%E5%A6%82%E6%9E%9C%E4%B8%80%E4%B8%AA%E4%BA%BA%E7%9A%84%E6%9C%8B%E5%8F%8B%E5%9C%88%E7%89%B9%E5%88%AB%E6%AD%A3%E5%B8%B8","published_at":null,"first_seen_at":"2026-03-14T02:28:43.039445Z","title_en":null,"title_zh":"如果一个人的朋友圈特别正常"},{"site_id":"tophub","site_name":"TopHub","source":"微博 · 热搜榜","title":"美军对伊石油出口枢纽猛烈空袭","url":"https://s.weibo.com/weibo?q=%E7%BE%8E%E5%86%9B%E5%AF%B9%E4%BC%8A%E7%9F%B3%E6%B2%B9%E5%87%BA%E5%8F%A3%E6%9E%A2%E7%BA%BD%E7%8C%9B%E7%83%88%E7%A9%BA%E8%A2%AD","published_at":null,"first_seen_at":"2026-03-14T02:28:43.039445Z","title_en":null,"title_zh":"美军对伊石油出口枢纽猛烈空袭"},{"site_id":"tophub","site_name":"TopHub","source":"微博 · 热搜榜","title":"两米二老外深圳就医视频火出圈","url":"https://s.weibo.com/weibo?q=%E4%B8%A4%E7%B1%B3%E4%BA%8C%E8%80%81%E5%A4%96%E6%B7%B1%E5%9C%B3%E5%B0%B1%E5%8C%BB%E8%A7%86%E9%A2%91%E7%81%AB%E5%87%BA%E5%9C%88","published_at":null,"first_seen_at":"2026-03-14T02:28:43.039445Z","title_en":null,"title_zh":"两米二老外深圳就医视频火出圈"},{"site_id":"tophub","site_name":"TopHub","source":"微博 · 热搜榜","title":"菠萝和凤梨到底啥区别","url":"https://s.weibo.com/weibo?q=%E8%8F%A0%E8%90%9D%E5%92%8C%E5%87%A4%E6%A2%A8%E5%88%B0%E5%BA%95%E5%95%A5%E5%8C%BA%E5%88%AB","published_at":null,"first_seen_at":"2026-03-14T02:28:43.039445Z","title_en":null,"title_zh":"菠萝和凤梨到底啥区别"},{"site_id":"tophub","site_name":"TopHub","source":"微博 · 热搜榜","title":"伊朗向以色列发动最猛烈空袭","url":"https://s.weibo.com/weibo?q=%E4%BC%8A%E6%9C%97%E5%90%91%E4%BB%A5%E8%89%B2%E5%88%97%E5%8F%91%E5%8A%A8%E6%9C%80%E7%8C%9B%E7%83%88%E7%A9%BA%E8%A2%AD","published_at":null,"first_seen_at":"2026-03-14T02:28:43.039445Z","title_en":null,"title_zh":"伊朗向以色列发动最猛烈空袭"},{"site_id":"tophub","site_name":"TopHub","source":"微博 · 热搜榜","title":"警方通报19岁男子无证驾驶致1死6伤","url":"https://s.weibo.com/weibo?q=%E8%AD%A6%E6%96%B9%E9%80%9A%E6%8A%A519%E5%B2%81%E7%94%B7%E5%AD%90%E6%97%A0%E8%AF%81%E9%A9%BE%E9%A9%B6%E8%87%B41%E6%AD%BB6%E4%BC%A4","published_at":null,"first_seen_at":"2026-03-14T02:28:43.039445Z","title_en":null,"title_zh":"警方通报19岁男子无证驾驶致1死6伤"},{"site_id":"tophub","site_name":"TopHub","source":"微博 · 热搜榜","title":"新能源车高速连跳3次空挡瞬间失速","url":"https://s.weibo.com/weibo?q=%E6%96%B0%E8%83%BD%E6%BA%90%E8%BD%A6%E9%AB%98%E9%80%9F%E8%BF%9E%E8%B7%B33%E6%AC%A1%E7%A9%BA%E6%8C%A1%E7%9E%AC%E9%97%B4%E5%A4%B1%E9%80%9F","published_at":null,"first_seen_at":"2026-03-14T02:28:43.039445Z","title_en":null,"title_zh":"新能源车高速连跳3次空挡瞬间失速"},{"site_id":"tophub","site_name":"TopHub","source":"微博 · 热搜榜","title":"逐玉崔千金宁死不出卖樊长玉","url":"https://s.weibo.com/weibo?q=%E9%80%90%E7%8E%89%E5%B4%94%E5%8D%83%E9%87%91%E5%AE%81%E6%AD%BB%E4%B8%8D%E5%87%BA%E5%8D%96%E6%A8%8A%E9%95%BF%E7%8E%89","published_at":null,"first_seen_at":"2026-03-14T02:28:43.039445Z","title_en":null,"title_zh":"逐玉崔千金宁死不出卖樊长玉"},{"site_id":"tophub","site_name":"TopHub","source":"微博 · 热搜榜","title":"32岁女子反复便血半年确诊肠癌","url":"https://s.weibo.com/weibo?q=32%E5%B2%81%E5%A5%B3%E5%AD%90%E5%8F%8D%E5%A4%8D%E4%BE%BF%E8%A1%80%E5%8D%8A%E5%B9%B4%E7%A1%AE%E8%AF%8A%E8%82%A0%E7%99%8C","published_at":null,"first_seen_at":"2026-03-14T02:28:43.039445Z","title_en":null,"title_zh":"32岁女子反复便血半年确诊肠癌"},{"site_id":"tophub","site_name":"TopHub","source":"微博 · 热搜榜","title":"以色列袭击伊朗高级核科学家","url":"https://s.weibo.com/weibo?q=%E4%BB%A5%E8%89%B2%E5%88%97%E8%A2%AD%E5%87%BB%E4%BC%8A%E6%9C%97%E9%AB%98%E7%BA%A7%E6%A0%B8%E7%A7%91%E5%AD%A6%E5%AE%B6","published_at":null,"first_seen_at":"2026-03-14T02:28:43.039445Z","title_en":null,"title_zh":"以色列袭击伊朗高级核科学家"},{"site_id":"tophub","site_name":"TopHub","source":"微博 · 热搜榜","title":"怀孕可能改变大脑结构","url":"https://s.weibo.com/weibo?q=%E6%80%80%E5%AD%95%E5%8F%AF%E8%83%BD%E6%94%B9%E5%8F%98%E5%A4%A7%E8%84%91%E7%BB%93%E6%9E%84","published_at":null,"first_seen_at":"2026-03-14T02:28:43.039445Z","title_en":null,"title_zh":"怀孕可能改变大脑结构"},{"site_id":"tophub","site_name":"TopHub","source":"微博 · 热搜榜","title":"田曦薇骑马这段夯爆了","url":"https://s.weibo.com/weibo?q=%E7%94%B0%E6%9B%A6%E8%96%87%E9%AA%91%E9%A9%AC%E8%BF%99%E6%AE%B5%E5%A4%AF%E7%88%86%E4%BA%86","published_at":null,"first_seen_at":"2026-03-14T02:28:43.039445Z","title_en":null,"title_zh":"田曦薇骑马这段夯爆了"},{"site_id":"tophub","site_name":"TopHub","source":"微博 · 热搜榜","title":"伊朗对美以发动47波攻击","url":"https://s.weibo.com/weibo?q=%E4%BC%8A%E6%9C%97%E5%AF%B9%E7%BE%8E%E4%BB%A5%E5%8F%91%E5%8A%A847%E6%B3%A2%E6%94%BB%E5%87%BB","published_at":null,"first_seen_at":"2026-03-14T02:28:43.039445Z","title_en":null,"title_zh":"伊朗对美以发动47波攻击"},{"site_id":"tophub","site_name":"TopHub","source":"微博 · 热搜榜","title":"5架美军加油机在沙特遭袭受损","url":"https://s.weibo.com/weibo?q=5%E6%9E%B6%E7%BE%8E%E5%86%9B%E5%8A%A0%E6%B2%B9%E6%9C%BA%E5%9C%A8%E6%B2%99%E7%89%B9%E9%81%AD%E8%A2%AD%E5%8F%97%E6%8D%9F","published_at":null,"first_seen_at":"2026-03-14T02:28:43.039445Z","title_en":null,"title_zh":"5架美军加油机在沙特遭袭受损"},{"site_id":"tophub","site_name":"TopHub","source":"微博 · 热搜榜","title":"杭州男生手搓3台机器人保研国科大","url":"https://s.weibo.com/weibo?q=%E6%9D%AD%E5%B7%9E%E7%94%B7%E7%94%9F%E6%89%8B%E6%90%933%E5%8F%B0%E6%9C%BA%E5%99%A8%E4%BA%BA%E4%BF%9D%E7%A0%94%E5%9B%BD%E7%A7%91%E5%A4%A7","published_at":null,"first_seen_at":"2026-03-14T02:28:43.039445Z","title_en":null,"title_zh":"杭州男生手搓3台机器人保研国科大"},{"site_id":"tophub","site_name":"TopHub","source":"微博 · 热搜榜","title":"澳洲遇难中国人疑为签证刷工作天数","url":"https://s.weibo.com/weibo?q=%E6%BE%B3%E6%B4%B2%E9%81%87%E9%9A%BE%E4%B8%AD%E5%9B%BD%E4%BA%BA%E7%96%91%E4%B8%BA%E7%AD%BE%E8%AF%81%E5%88%B7%E5%B7%A5%E4%BD%9C%E5%A4%A9%E6%95%B0","published_at":null,"first_seen_at":"2026-03-14T02:28:43.039445Z","title_en":null,"title_zh":"澳洲遇难中国人疑为签证刷工作天数"},{"site_id":"tophub","site_name":"TopHub","source":"微博 · 热搜榜","title":"库里38岁了","url":"https://s.weibo.com/weibo?q=%E5%BA%93%E9%87%8C38%E5%B2%81%E4%BA%86","published_at":null,"first_seen_at":"2026-03-14T02:28:43.039445Z","title_en":null,"title_zh":"库里38岁了"},{"site_id":"tophub","site_name":"TopHub","source":"微博 · 热搜榜","title":"多名配音演员发函要求停止AI侵权","url":"https://s.weibo.com/weibo?q=%E5%A4%9A%E5%90%8D%E9%85%8D%E9%9F%B3%E6%BC%94%E5%91%98%E5%8F%91%E5%87%BD%E8%A6%81%E6%B1%82%E5%81%9C%E6%AD%A2AI%E4%BE%B5%E6%9D%83","published_at":null,"first_seen_at":"2026-03-14T02:28:43.039445Z","title_en":null,"title_zh":"多名配音演员发函要求停止AI侵权"},{"site_id":"tophub","site_name":"TopHub","source":"微博 · 热搜榜","title":"深圳一医院全员说英语震惊老外","url":"https://s.weibo.com/weibo?q=%E6%B7%B1%E5%9C%B3%E4%B8%80%E5%8C%BB%E9%99%A2%E5%85%A8%E5%91%98%E8%AF%B4%E8%8B%B1%E8%AF%AD%E9%9C%87%E6%83%8A%E8%80%81%E5%A4%96","published_at":null,"first_seen_at":"2026-03-14T02:28:43.039445Z","title_en":null,"title_zh":"深圳一医院全员说英语震惊老外"},{"site_id":"tophub","site_name":"TopHub","source":"微博 · 热搜榜","title":"A股每天4小时交易时间够用吗","url":"https://s.weibo.com/weibo?q=A%E8%82%A1%E6%AF%8F%E5%A4%A94%E5%B0%8F%E6%97%B6%E4%BA%A4%E6%98%93%E6%97%B6%E9%97%B4%E5%A4%9F%E7%94%A8%E5%90%97","published_at":null,"first_seen_at":"2026-03-14T02:28:43.039445Z","title_en":null,"title_zh":"A股每天4小时交易时间够用吗"},{"site_id":"tophub","site_name":"TopHub","source":"微博 · 热搜榜","title":"GEN上单回应Bin","url":"https://s.weibo.com/weibo?q=GEN%E4%B8%8A%E5%8D%95%E5%9B%9E%E5%BA%94Bin","published_at":null,"first_seen_at":"2026-03-14T02:28:43.039445Z","title_en":null,"title_zh":"GEN上单回应Bin"},{"site_id":"tophub","site_name":"TopHub","source":"微信 · 24h热文榜","title":"说说那些我买到就祛魅的东西","url":"https://mp.weixin.qq.com/s/urUlgXbmoLCRemCDtaq_zA","published_at":null,"first_seen_at":"2026-03-14T02:28:43.039445Z","title_en":null,"title_zh":"说说那些我买到就祛魅的东西"},{"site_id":"tophub","site_name":"TopHub","source":"微信 · 24h热文榜","title":"东北玉米行情变了！","url":"https://mp.weixin.qq.com/s/NCTXvexmqOSpDctHqN0dtQ","published_at":null,"first_seen_at":"2026-03-14T02:28:43.039445Z","title_en":null,"title_zh":"东北玉米行情变了！"},{"site_id":"tophub","site_name":"TopHub","source":"微信 · 24h热文榜","title":"穿长裙拍照，几个生活感姿势，明媚漂亮，优雅知性，落落大方有韵味","url":"https://mp.weixin.qq.com/s?__biz=MzkzMjY1MTUyMw%3D%3D&mid=2247496790&idx=1&sn=c58f51f07c3333c3c9f88fd448f8eb6a&chksm=240015","published_at":null,"first_seen_at":"2026-03-14T02:28:43.039445Z","title_en":null,"title_zh":"穿长裙拍照，几个生活感姿势，明媚漂亮，优雅知性，落落大方有韵味"},{"site_id":"tophub","site_name":"TopHub","source":"微信 · 24h热文榜","title":"早知天下事","url":"https://mp.weixin.qq.com/s/67_yIcAyMdB8gvft7g4i8Q","published_at":null,"first_seen_at":"2026-03-14T02:28:43.039445Z","title_en":null,"title_zh":"早知天下事"},{"site_id":"tophub","site_name":"TopHub","source":"微信 · 24h热文榜","title":"我婆每次打完针都把针头弄弯，以免扎伤收垃圾的人","url":"https://mp.weixin.qq.com/s/Sig5ZhSlgqm8XFSsYfIODw","published_at":null,"first_seen_at":"2026-03-14T02:28:43.039445Z","title_en":null,"title_zh":"我婆每次打完针都把针头弄弯，以免扎伤收垃圾的人"},{"site_id":"tophub","site_name":"TopHub","source":"百度 · 实时热点","title":"车辆高速多次失速 售后称是超速保护","url":"https://www.baidu.com/s?wd=%E8%BD%A6%E8%BE%86%E9%AB%98%E9%80%9F%E5%A4%9A%E6%AC%A1%E5%A4%B1%E9%80%9F+%E5%94%AE%E5%90%8E%E7%A7%B0%E6%98%AF%E8%B6%85%E9%80%9F%E4%BF%9D%E6%8A%A4","published_at":null,"first_seen_at":"2026-03-14T02:28:43.039445Z","title_en":null,"title_zh":"车辆高速多次失速 售后称是超速保护"},{"site_id":"tophub","site_name":"TopHub","source":"百度 · 实时热点","title":"“苹果税”终于降了 你能省多少钱","url":"https://www.baidu.com/s?wd=%E2%80%9C%E8%8B%B9%E6%9E%9C%E7%A8%8E%E2%80%9D%E7%BB%88%E4%BA%8E%E9%99%8D%E4%BA%86+%E4%BD%A0%E8%83%BD%E7%9C%81%E5%A4%9A%E5%B0%91%E9%92%B1","published_at":null,"first_seen_at":"2026-03-14T02:28:43.039445Z","title_en":null,"title_zh":"“苹果税”终于降了 你能省多少钱"},{"site_id":"tophub","site_name":"TopHub","source":"百度 · 实时热点","title":"张颂文硬气回应AI冲击影视行业","url":"https://www.baidu.com/s?wd=%E5%BC%A0%E9%A2%82%E6%96%87%E7%A1%AC%E6%B0%94%E5%9B%9E%E5%BA%94AI%E5%86%B2%E5%87%BB%E5%BD%B1%E8%A7%86%E8%A1%8C%E4%B8%9A","published_at":null,"first_seen_at":"2026-03-14T02:28:43.039445Z","title_en":null,"title_zh":"张颂文硬气回应AI冲击影视行业"},{"site_id":"tophub","site_name":"TopHub","source":"百度 · 实时热点","title":"无法兑现的“终身质保”：车企玩噱头","url":"https://www.baidu.com/s?wd=%E6%97%A0%E6%B3%95%E5%85%91%E7%8E%B0%E7%9A%84%E2%80%9C%E7%BB%88%E8%BA%AB%E8%B4%A8%E4%BF%9D%E2%80%9D%EF%BC%9A%E8%BD%A6%E4%BC%81%E7%8E%A9%E5%99%B1%E5%A4%B4","published_at":null,"first_seen_at":"2026-03-14T02:28:43.039445Z","title_en":null,"title_zh":"无法兑现的“终身质保”：车企玩噱头"},{"site_id":"tophub","site_name":"TopHub","source":"百度 · 实时热点","title":"比亚迪宣布闪充站建设进度","url":"https://www.baidu.com/s?wd=%E6%AF%94%E4%BA%9A%E8%BF%AA%E5%AE%A3%E5%B8%83%E9%97%AA%E5%85%85%E7%AB%99%E5%BB%BA%E8%AE%BE%E8%BF%9B%E5%BA%A6","published_at":null,"first_seen_at":"2026-03-14T02:28:43.039445Z","title_en":null,"title_zh":"比亚迪宣布闪充站建设进度"},{"site_id":"tophub","site_name":"TopHub","source":"百度 · 实时热点","title":"央行将开展5000亿元买断式逆回购","url":"https://www.baidu.com/s?wd=%E5%A4%AE%E8%A1%8C%E5%B0%86%E5%BC%80%E5%B1%955000%E4%BA%BF%E5%85%83%E4%B9%B0%E6%96%AD%E5%BC%8F%E9%80%86%E5%9B%9E%E8%B4%AD","published_at":null,"first_seen_at":"2026-03-14T02:28:43.039445Z","title_en":null,"title_zh":"央行将开展5000亿元买断式逆回购"},{"site_id":"tophub","site_name":"TopHub","source":"百度 · 实时热点","title":"注意！这种“催收短信”专骗你钱","url":"https://www.baidu.com/s?wd=%E6%B3%A8%E6%84%8F%EF%BC%81%E8%BF%99%E7%A7%8D%E2%80%9C%E5%82%AC%E6%94%B6%E7%9F%AD%E4%BF%A1%E2%80%9D%E4%B8%93%E9%AA%97%E4%BD%A0%E9%92%B1","published_at":null,"first_seen_at":"2026-03-14T02:28:43.039445Z","title_en":null,"title_zh":"注意！这种“催收短信”专骗你钱"},{"site_id":"tophub","site_name":"TopHub","source":"百度 · 实时热点","title":"扬州舰30分钟救起10位遇险渔民","url":"https://www.baidu.com/s?wd=%E6%89%AC%E5%B7%9E%E8%88%B030%E5%88%86%E9%92%9F%E6%95%91%E8%B5%B710%E4%BD%8D%E9%81%87%E9%99%A9%E6%B8%94%E6%B0%91","published_at":null,"first_seen_at":"2026-03-14T02:28:43.039445Z","title_en":null,"title_zh":"扬州舰30分钟救起10位遇险渔民"},{"site_id":"tophub","site_name":"TopHub","source":"百度 · 实时热点","title":"茅台改革：非标产品全面实行代销制","url":"https://www.baidu.com/s?wd=%E8%8C%85%E5%8F%B0%E6%94%B9%E9%9D%A9%EF%BC%9A%E9%9D%9E%E6%A0%87%E4%BA%A7%E5%93%81%E5%85%A8%E9%9D%A2%E5%AE%9E%E8%A1%8C%E4%BB%A3%E9%94%80%E5%88%B6","published_at":null,"first_seen_at":"2026-03-14T02:28:43.039445Z","title_en":null,"title_zh":"茅台改革：非标产品全面实行代销制"},{"site_id":"tophub","site_name":"TopHub","source":"36氪 · 24小时热榜","title":"中医考证生意火爆：有人花五万挂名，只为一张证","url":"https://www.36kr.com/p/3720649131702914","published_at":null,"first_seen_at":"2026-03-14T02:28:43.039445Z","title_en":null,"title_zh":"中医考证生意火爆：有人花五万挂名，只为一张证"},{"site_id":"tophub","site_name":"TopHub","source":"Readhub · AI","title":"与科研人员携手“取真经”，超级科研合伙人“大圣”上线","url":"https://news.sciencenet.cn/htmlnews/2026/3/561370.shtm","published_at":null,"first_seen_at":"2026-03-14T02:28:43.039445Z","title_en":null,"title_zh":"与科研人员携手“取真经”，超级科研合伙人“大圣”上线"},{"site_id":"tophub","site_name":"TopHub","source":"Readhub · AI","title":"俄罗斯Yandex为“Alice”虚拟助手创建新事业部推动AI购物落地","url":"https://www.amz123.com/kx/arzZfNMK","published_at":null,"first_seen_at":"2026-03-14T02:28:43.039445Z","title_en":null,"title_zh":"俄罗斯Yandex为“Alice”虚拟助手创建新事业部推动AI购物落地"},{"site_id":"tophub","site_name":"TopHub","source":"Readhub · AI","title":"马拉比中国行解密DeepMind：哈萨比斯错失大模型先机的真相","url":"https://www.tmtpost.com/7913014.html","published_at":null,"first_seen_at":"2026-03-14T02:28:43.039445Z","title_en":null,"title_zh":"马拉比中国行解密DeepMind：哈萨比斯错失大模型先机的真相"},{"site_id":"tophub","site_name":"TopHub","source":"Readhub · AI","title":"OpenClaw爆火，App时代要结束了？","url":"https://www.tmtpost.com/7913500.html","published_at":null,"first_seen_at":"2026-03-14T02:28:43.039445Z","title_en":null,"title_zh":"OpenClaw爆火，App时代要结束了？"},{"site_id":"tophub","site_name":"TopHub","source":"Readhub · AI","title":"AI赋能，新研究提出气候政策评估新范式","url":"https://news.sciencenet.cn/htmlnews/2026/3/561353.shtm","published_at":null,"first_seen_at":"2026-03-14T02:28:43.039445Z","title_en":null,"title_zh":"AI赋能，新研究提出气候政策评估新范式"},{"site_id":"tophub","site_name":"TopHub","source":"Readhub · AI","title":"xAI聘请AI初创公司Thinking Machines创始成员，参与Grok AI模型训练工作","url":"https://www.tmtpost.com/nictation/7914033.html","published_at":null,"first_seen_at":"2026-03-14T02:28:43.039445Z","title_en":null,"title_zh":"xAI聘请AI初创公司Thinking Machines创始成员，参与Grok AI模型训练工作"},{"site_id":"tophub","site_name":"TopHub","source":"Readhub · AI","title":"结合AI与构象动力学驱动的蛋白质设计研究获进展","url":"https://news.sciencenet.cn/htmlnews/2026/3/561343.shtm","published_at":null,"first_seen_at":"2026-03-14T02:28:43.039445Z","title_en":null,"title_zh":"结合AI与构象动力学驱动的蛋白质设计研究获进展"},{"site_id":"tophub","site_name":"TopHub","source":"Readhub · AI","title":"万物皆可 “养龙虾”，20万人现场围观AI家电大混战｜AWE 2026","url":"https://www.tmtpost.com/7913257.html","published_at":null,"first_seen_at":"2026-03-14T02:28:43.039445Z","title_en":null,"title_zh":"万物皆可 “养龙虾”，20万人现场围观AI家电大混战｜AWE 2026"},{"site_id":"tophub","site_name":"TopHub","source":"快手 · 实时热榜","title":"剑来卡点舞","url":"https://index.e.kuaishou.com/rank/hotDetail?keyword=%E5%89%91%E6%9D%A5%E5%8D%A1%E7%82%B9%E8%88%9E&rankType=1","published_at":null,"first_seen_at":"2026-03-14T02:28:43.039445Z","title_en":null,"title_zh":"剑来卡点舞"},{"site_id":"tophub","site_name":"TopHub","source":"快手 · 实时热榜","title":"宁夏发布315维权案例","url":"https://index.e.kuaishou.com/rank/hotDetail?keyword=%E5%AE%81%E5%A4%8F%E5%8F%91%E5%B8%83315%E7%BB%B4%E6%9D%83%E6%A1%88%E4%BE%8B&rankType=1","published_at":null,"first_seen_at":"2026-03-14T02:28:43.039445Z","title_en":null,"title_zh":"宁夏发布315维权案例"},{"site_id":"tophub","site_name":"TopHub","source":"快手 · 实时热榜","title":"谢征谢危同款醋王","url":"https://index.e.kuaishou.com/rank/hotDetail?keyword=%E8%B0%A2%E5%BE%81%E8%B0%A2%E5%8D%B1%E5%90%8C%E6%AC%BE%E9%86%8B%E7%8E%8B&rankType=1","published_at":null,"first_seen_at":"2026-03-14T02:28:43.039445Z","title_en":null,"title_zh":"谢征谢危同款醋王"},{"site_id":"tophub","site_name":"TopHub","source":"快手 · 实时热榜","title":"武城集中销毁假冒伪劣商品","url":"https://index.e.kuaishou.com/rank/hotDetail?keyword=%E6%AD%A6%E5%9F%8E%E9%9B%86%E4%B8%AD%E9%94%80%E6%AF%81%E5%81%87%E5%86%92%E4%BC%AA%E5%8A%A3%E5%95%86%E5%93%81&rankType=1","published_at":null,"first_seen_at":"2026-03-14T02:28:43.039445Z","title_en":null,"title_zh":"武城集中销毁假冒伪劣商品"},{"site_id":"tophub","site_name":"TopHub","source":"快手 · 实时热榜","title":"318公路展亮相F1中国站","url":"https://index.e.kuaishou.com/rank/hotDetail?keyword=318%E5%85%AC%E8%B7%AF%E5%B1%95%E4%BA%AE%E7%9B%B8F1%E4%B8%AD%E5%9B%BD%E7%AB%99&rankType=1","published_at":null,"first_seen_at":"2026-03-14T02:28:43.039445Z","title_en":null,"title_zh":"318公路展亮相F1中国站"},{"site_id":"tophub","site_name":"TopHub","source":"快手 · 实时热榜","title":"湖南免费HPV疫苗已到位","url":"https://index.e.kuaishou.com/rank/hotDetail?keyword=%E6%B9%96%E5%8D%97%E5%85%8D%E8%B4%B9HPV%E7%96%AB%E8%8B%97%E5%B7%B2%E5%88%B0%E4%BD%8D&rankType=1","published_at":null,"first_seen_at":"2026-03-14T02:28:43.039445Z","title_en":null,"title_zh":"湖南免费HPV疫苗已到位"},{"site_id":"tophub","site_name":"TopHub","source":"虎扑社区 · 步行街热帖","title":"我们五个谁看起来最有感觉","url":"https://bbs.hupu.com/637889870.html","published_at":null,"first_seen_at":"2026-03-14T02:28:43.039445Z","title_en":null,"title_zh":"我们五个谁看起来最有感觉"},{"site_id":"tophub","site_name":"TopHub","source":"虎扑社区 · 步行街热帖","title":"i7重回学生时代","url":"https://bbs.hupu.com/637890425.html","published_at":null,"first_seen_at":"2026-03-14T02:28:43.039445Z","title_en":null,"title_zh":"i7重回学生时代"},{"site_id":"tophub","site_name":"TopHub","source":"虎扑社区 · 步行街热帖","title":"分享一些局部","url":"https://bbs.hupu.com/637889991.html","published_at":null,"first_seen_at":"2026-03-14T02:28:43.039445Z","title_en":null,"title_zh":"分享一些局部"},{"site_id":"tophub","site_name":"TopHub","source":"虎扑社区 · 步行街热帖","title":"网贷欠了几十个，看到很多广告说可以协商解决","url":"https://bbs.hupu.com/637889860.html","published_at":null,"first_seen_at":"2026-03-14T02:28:43.039445Z","title_en":null,"title_zh":"网贷欠了几十个，看到很多广告说可以协商解决"},{"site_id":"tophub","site_name":"TopHub","source":"虎扑社区 · 步行街热帖","title":"兄弟们，过来交流下经验","url":"https://bbs.hupu.com/637890016.html","published_at":null,"first_seen_at":"2026-03-14T02:28:43.039445Z","title_en":null,"title_zh":"兄弟们，过来交流下经验"},{"site_id":"tophub","site_name":"TopHub","source":"虎扑社区 · 步行街热帖","title":"你们有没有发现，近些年面包价格贵的离谱？","url":"https://bbs.hupu.com/637889291.html","published_at":null,"first_seen_at":"2026-03-14T02:28:43.039445Z","title_en":null,"title_zh":"你们有没有发现，近些年面包价格贵的离谱？"},{"site_id":"tophub","site_name":"TopHub","source":"虎扑社区 · 步行街热帖","title":"如果你认识她会介绍给你的好兄弟吗","url":"https://bbs.hupu.com/637888779.html","published_at":null,"first_seen_at":"2026-03-14T02:28:43.039445Z","title_en":null,"title_zh":"如果你认识她会介绍给你的好兄弟吗"},{"site_id":"tophub","site_name":"TopHub","source":"虎扑社区 · 步行街热帖","title":"跟一个女生约吃饭，出去玩","url":"https://bbs.hupu.com/637888988.html","published_at":null,"first_seen_at":"2026-03-14T02:28:43.039445Z","title_en":null,"title_zh":"跟一个女生约吃饭，出去玩"},{"site_id":"tophub","site_name":"TopHub","source":"虎扑社区 · 步行街热帖","title":"大哥力度掌握的真好，一招没少出是一招也没挨到","url":"https://bbs.hupu.com/637888566.html","published_at":null,"first_seen_at":"2026-03-14T02:28:43.039445Z","title_en":null,"title_zh":"大哥力度掌握的真好，一招没少出是一招也没挨到"},{"site_id":"tophub","site_name":"TopHub","source":"虎扑社区 · 步行街热帖","title":"汶川大地震时15名空降兵从5000米高空盲跳，难度有多大？","url":"https://bbs.hupu.com/637886616.html","published_at":null,"first_seen_at":"2026-03-14T02:28:43.039445Z","title_en":null,"title_zh":"汶川大地震时15名空降兵从5000米高空盲跳，难度有多大？"},{"site_id":"tophub","site_name":"TopHub","source":"虎扑社区 · 步行街热帖","title":"霉里贱播主探访中国农村，直接表示这里让人“绝望”，啥意思？","url":"https://bbs.hupu.com/637888377.html","published_at":null,"first_seen_at":"2026-03-14T02:28:43.039445Z","title_en":null,"title_zh":"霉里贱播主探访中国农村，直接表示这里让人“绝望”，啥意思？"},{"site_id":"tophub","site_name":"TopHub","source":"虎扑社区 · 步行街热帖","title":"这种地铁打人事件会怎么处罚？","url":"https://bbs.hupu.com/637886250.html","published_at":null,"first_seen_at":"2026-03-14T02:28:43.039445Z","title_en":null,"title_zh":"这种地铁打人事件会怎么处罚？"},{"site_id":"tophub","site_name":"TopHub","source":"虎扑社区 · 步行街热帖","title":"女神分手我去安慰，结局舒服了","url":"https://bbs.hupu.com/637885031.html","published_at":null,"first_seen_at":"2026-03-14T02:28:43.039445Z","title_en":null,"title_zh":"女神分手我去安慰，结局舒服了"},{"site_id":"tophub","site_name":"TopHub","source":"淘宝 · TOP100人气榜","title":"【任选5件】稻香村中式点心糕点组合 原价¥59.9 券后¥29.9","url":"https://tophub.today/link?domain=taobao.com&url=https%3A%2F%2Fremai.today%2Flink%2F1%2FJDKv6BDCRtqwdnKGN7TXD7Cvt6-YJGeOZNHBbmJwW0gfz","published_at":null,"first_seen_at":"2026-03-14T02:28:43.039445Z","title_en":null,"title_zh":"【任选5件】稻香村中式点心糕点组合 原价¥59.9 券后¥29.9"},{"site_id":"tophub","site_name":"TopHub","source":"淘宝 · TOP100人气榜","title":"大额秒杀！妇炎洁内裤清洗液300g+100gx2袋 原价¥28.9 券后¥19.9","url":"https://tophub.today/link?domain=taobao.com&url=https%3A%2F%2Fremai.today%2Flink%2F1%2Fz52n8NAfetan4VyW6PUvwqcdtj-88DbxaKC52GYOBqxSY","published_at":null,"first_seen_at":"2026-03-14T02:28:43.039445Z","title_en":null,"title_zh":"大额秒杀！妇炎洁内裤清洗液300g+100gx2袋 原价¥28.9 券后¥19.9"},{"site_id":"tophub","site_name":"TopHub","source":"淘宝 · TOP100人气榜","title":"思念品牌全家福合集8件 原价¥204 券后¥49","url":"https://tophub.today/link?domain=taobao.com&url=https%3A%2F%2Fremai.today%2Flink%2F1%2FAQ4gW3jizt47OXpMrbSmBwUvtO-4V2A3ZgI8z2VGvKXUOz","published_at":null,"first_seen_at":"2026-03-14T02:28:43.039445Z","title_en":null,"title_zh":"思念品牌全家福合集8件 原价¥204 券后¥49"},{"site_id":"tophub","site_name":"TopHub","source":"淘宝 · TOP100人气榜","title":"19.9元曼秀雷敦夏季防晒喷雾防嗮霜100ml 原价¥54.9 券后¥19.9","url":"https://tophub.today/link?domain=taobao.com&url=https%3A%2F%2Fremai.today%2Flink%2F1%2Fk3BOWoqrTYtaGPzJoX7TG50CPt5-ANgJ0akHGRapqeaPhY6","published_at":null,"first_seen_at":"2026-03-14T02:28:43.039445Z","title_en":null,"title_zh":"19.9元曼秀雷敦夏季防晒喷雾防嗮霜100ml 原价¥54.9 券后¥19.9"},{"site_id":"tophub","site_name":"TopHub","source":"淘宝 · TOP100人气榜","title":"【榄菊】电热蚊香液4瓶1器 原价¥29.9 券后¥19.9","url":"https://tophub.today/link?domain=taobao.com&url=https%3A%2F%2Fremai.today%2Flink%2F1%2FG8NVNvRF8tYmaNn7RQhYqkIQtJ-YJGeOZNHdAY36YzmSW","published_at":null,"first_seen_at":"2026-03-14T02:28:43.039445Z","title_en":null,"title_zh":"【榄菊】电热蚊香液4瓶1器 原价¥29.9 券后¥19.9"},{"site_id":"tophub","site_name":"TopHub","source":"淘宝 · TOP100人气榜","title":"冈本进口超薄裸入避孕套14只 原价¥76 券后¥24","url":"https://tophub.today/link?domain=taobao.com&url=https%3A%2F%2Fremai.today%2Flink%2F1%2FrepaZO5UOtVPKe4Kj8f609tqtg-7no8vaXH9ZqK6k4c9","published_at":null,"first_seen_at":"2026-03-14T02:28:43.039445Z","title_en":null,"title_zh":"冈本进口超薄裸入避孕套14只 原价¥76 券后¥24"},{"site_id":"tophub","site_name":"TopHub","source":"淘宝 · TOP100人气榜","title":"强生美肌蜜桃香氛沐浴露保湿长效留香 原价¥76.9 券后¥32.9","url":"https://tophub.today/link?domain=taobao.com&url=https%3A%2F%2Fremai.today%2Flink%2F1%2FAYebJOGFzt47OX7a2PimwqSvtO-eQGMq6ACG6MKQQJ4c9d","published_at":null,"first_seen_at":"2026-03-14T02:28:43.039445Z","title_en":null,"title_zh":"强生美肌蜜桃香氛沐浴露保湿长效留香 原价¥76.9 券后¥32.9"},{"site_id":"tophub","site_name":"TopHub","source":"淘宝 · TOP100人气榜","title":"原喵派海盐小苏打猫砂2.1kg 原价¥9.9 券后¥6.9","url":"https://tophub.today/link?domain=taobao.com&url=https%3A%2F%2Fremai.today%2Flink%2F1%2FkrGyorASYtaGPjjDxMsG5jtPtJ-pBx2XAdI2d4p54QPtA","published_at":null,"first_seen_at":"2026-03-14T02:28:43.039445Z","title_en":null,"title_zh":"原喵派海盐小苏打猫砂2.1kg 原价¥9.9 券后¥6.9"},{"site_id":"tophub","site_name":"TopHub","source":"华尔街见闻 · 日排行","title":"美媒曝特朗普在七国集团会议上“吹嘘”伊朗“即将投降”","url":"https://wallstreetcn.com/articles/3767468","published_at":null,"first_seen_at":"2026-03-14T02:28:43.039445Z","title_en":null,"title_zh":"美媒曝特朗普在七国集团会议上“吹嘘”伊朗“即将投降”"},{"site_id":"tophub","site_name":"TopHub","source":"新浪财经新闻 · 点击量排行","title":"伊朗高层姿态强硬 以强势言辞和公开游行直面特朗普","url":"https://finance.sina.com.cn/stock/usstock/c/2026-03-14/doc-inhqwkfa0895057.shtml","published_at":null,"first_seen_at":"2026-03-14T02:28:43.039445Z","title_en":null,"title_zh":"伊朗高层姿态强硬 以强势言辞和公开游行直面特朗普"},{"site_id":"tophub","site_name":"TopHub","source":"北大未名 · 全站热门话题","title":"[出] 500 元京东 E 卡","url":"https://bbs.pku.edu.cn/v2/post-read.php?bid=71&threadid=19000844","published_at":null,"first_seen_at":"2026-03-14T02:28:43.039445Z","title_en":null,"title_zh":"[出] 500 元京东 E 卡"},{"site_id":"tophub","site_name":"TopHub","source":"北大未名 · 首页推荐","title":"专门开个记录健身、呼吸和断舍离的日记","url":"https://bbs.pku.edu.cn/v2/post-read.php?bid=361&threadid=19000695","published_at":null,"first_seen_at":"2026-03-14T02:28:43.039445Z","title_en":null,"title_zh":"专门开个记录健身、呼吸和断舍离的日记"},{"site_id":"tophub","site_name":"TopHub","source":"厦门小鱼 · 今日热帖","title":"有没会修手机，公司缺人","url":"http://bbs.xmfish.com/read-htm-tid-18309893.html","published_at":null,"first_seen_at":"2026-03-14T02:28:43.039445Z","title_en":null,"title_zh":"有没会修手机，公司缺人"},{"site_id":"tophub","site_name":"TopHub","source":"3DM游戏网 · 最新新闻","title":"谁更夯？《生化危机9》和《荒野大镖客2》掀布料对比","url":"https://m.3dmgame.com/news/202603/3939705.html","published_at":null,"first_seen_at":"2026-03-14T02:28:43.039445Z","title_en":null,"title_zh":"谁更夯？《生化危机9》和《荒野大镖客2》掀布料对比"},{"site_id":"tophub","site_name":"TopHub","source":"新浪体育新闻 · 点击量排行","title":"足彩彩果:埃尔弗斯堡爆4倍冷负 都灵4-1帕尔马","url":"https://sports.sina.com.cn/l/2026-03-14/doc-inhqxfks0544463.shtml","published_at":null,"first_seen_at":"2026-03-14T02:28:43.039445Z","title_en":null,"title_zh":"足彩彩果:埃尔弗斯堡爆4倍冷负 都灵4-1帕尔马"},{"site_id":"tophub","site_name":"TopHub","source":"虎扑社区 · NBA论坛热帖","title":"[流言板]阿德巴约：要怪就怪奇才教练，不包夹单节30分的我","url":"https://bbs.hupu.com/637888712.html","published_at":null,"first_seen_at":"2026-03-14T02:28:43.039445Z","title_en":null,"title_zh":"[流言板]阿德巴约：要怪就怪奇才教练，不包夹单节30分的我"},{"site_id":"tophub","site_name":"TopHub","source":"虎扑社区 · NBA论坛热帖","title":"[流言板]火箭首发：阿门、伊森、杜兰特、小贾巴里、芬尼-史密斯","url":"https://bbs.hupu.com/637888412.html","published_at":null,"first_seen_at":"2026-03-14T02:28:43.039445Z","title_en":null,"title_zh":"[流言板]火箭首发：阿门、伊森、杜兰特、小贾巴里、芬尼-史密斯"},{"site_id":"tophub","site_name":"TopHub","source":"虎扑社区 · NBA论坛热帖","title":"[流言板]哈登半场7投3中得到10分6篮板5助攻1抢断，正负值+21","url":"https://bbs.hupu.com/637889178.html","published_at":null,"first_seen_at":"2026-03-14T02:28:43.039445Z","title_en":null,"title_zh":"[流言板]哈登半场7投3中得到10分6篮板5助攻1抢断，正负值+21"},{"site_id":"tophub","site_name":"TopHub","source":"虎扑社区 · NBA论坛热帖","title":"[流言板]湖人伤情：斯马特已经从伤病名单移除，海斯明日可能出战","url":"https://bbs.hupu.com/637888659.html","published_at":null,"first_seen_at":"2026-03-14T02:28:43.039445Z","title_en":null,"title_zh":"[流言板]湖人伤情：斯马特已经从伤病名单移除，海斯明日可能出战"},{"site_id":"tophub","site_name":"TopHub","source":"虎扑社区 · NBA论坛热帖","title":"[流言板]奥多姆：我梦到科比，他说“来世并不像人们想象的那样”","url":"https://bbs.hupu.com/637888523.html","published_at":null,"first_seen_at":"2026-03-14T02:28:43.039445Z","title_en":null,"title_zh":"[流言板]奥多姆：我梦到科比，他说“来世并不像人们想象的那样”"},{"site_id":"tophub","site_name":"TopHub","source":"虎扑社区 · NBA论坛热帖","title":"[流言板]掘金伤情：明日对阵湖人默里和戈登可能出战、沃特森缺席","url":"https://bbs.hupu.com/637889049.html","published_at":null,"first_seen_at":"2026-03-14T02:28:43.039445Z","title_en":null,"title_zh":"[流言板]掘金伤情：明日对阵湖人默里和戈登可能出战、沃特森缺席"},{"site_id":"tophub","site_name":"TopHub","source":"虎扑社区 · NBA论坛热帖","title":"[流言板]严阵以待！快船众将步入今日比赛场馆，伦纳德低调出镜","url":"https://bbs.hupu.com/637889740.html","published_at":null,"first_seen_at":"2026-03-14T02:28:43.039445Z","title_en":null,"title_zh":"[流言板]严阵以待！快船众将步入今日比赛场馆，伦纳德低调出镜"},{"site_id":"tophub","site_name":"TopHub","source":"虎扑社区 · NBA论坛热帖","title":"天呐  风雪27分了  真被奥特教练激活了","url":"https://bbs.hupu.com/637889543.html","published_at":null,"first_seen_at":"2026-03-14T02:28:43.039445Z","title_en":null,"title_zh":"天呐  风雪27分了  真被奥特教练激活了"},{"site_id":"tophub","site_name":"TopHub","source":"虎扑社区 · NBA论坛热帖","title":"[流言板]Spears：爱德华兹今日很可能出战对阵勇士的比赛","url":"https://bbs.hupu.com/637889303.html","published_at":null,"first_seen_at":"2026-03-14T02:28:43.039445Z","title_en":null,"title_zh":"[流言板]Spears：爱德华兹今日很可能出战对阵勇士的比赛"},{"site_id":"tophub","site_name":"TopHub","source":"虎扑社区 · NBA论坛热帖","title":"[流言板]哈登弧顶后撤步三分投进，内突外投连得5分正负值+19","url":"https://bbs.hupu.com/637888975.html","published_at":null,"first_seen_at":"2026-03-14T02:28:43.039445Z","title_en":null,"title_zh":"[流言板]哈登弧顶后撤步三分投进，内突外投连得5分正负值+19"},{"site_id":"tophub","site_name":"TopHub","source":"虎扑社区 · NBA论坛热帖","title":"[流言板]史密斯头部与米西相撞血流不止，经过更衣室调整重回赛场","url":"https://bbs.hupu.com/637888875.html","published_at":null,"first_seen_at":"2026-03-14T02:28:43.039445Z","title_en":null,"title_zh":"[流言板]史密斯头部与米西相撞血流不止，经过更衣室调整重回赛场"},{"site_id":"tophub","site_name":"TopHub","source":"虎扑社区 · NBA论坛热帖","title":"[流言板]丹尼-格林谈阿德巴约83分：了不起，我是发自内心地替他高兴","url":"https://bbs.hupu.com/637888337.html","published_at":null,"first_seen_at":"2026-03-14T02:28:43.039445Z","title_en":null,"title_zh":"[流言板]丹尼-格林谈阿德巴约83分：了不起，我是发自内心地替他高兴"},{"site_id":"tophub","site_name":"TopHub","source":"虎扑社区 · NBA论坛热帖","title":"[流言板]杰伦-格林三分再中，开局三分3中3连砍9分打停猛龙","url":"https://bbs.hupu.com/637888479.html","published_at":null,"first_seen_at":"2026-03-14T02:28:43.039445Z","title_en":null,"title_zh":"[流言板]杰伦-格林三分再中，开局三分3中3连砍9分打停猛龙"},{"site_id":"tophub","site_name":"TopHub","source":"虎扑社区 · NBA论坛热帖","title":"19季后赛莱昂纳德只有11诺维斯基可以对比","url":"https://bbs.hupu.com/637888335.html","published_at":null,"first_seen_at":"2026-03-14T02:28:43.039445Z","title_en":null,"title_zh":"19季后赛莱昂纳德只有11诺维斯基可以对比"},{"site_id":"tophub","site_name":"TopHub","source":"虎扑社区 · NBA论坛热帖","title":"[流言板]骑士公布首发：米切尔，哈登，埃利斯，韦德，莫布利","url":"https://bbs.hupu.com/637888247.html","published_at":null,"first_seen_at":"2026-03-14T02:28:43.039445Z","title_en":null,"title_zh":"[流言板]骑士公布首发：米切尔，哈登，埃利斯，韦德，莫布利"},{"site_id":"tophub","site_name":"TopHub","source":"虎扑社区 · NBA论坛热帖","title":"[流言板]杜兰特快攻反击单臂暴扣连拿5分，目前个人已砍下21分5板5助","url":"https://bbs.hupu.com/637890081.html","published_at":null,"first_seen_at":"2026-03-14T02:28:43.039445Z","title_en":null,"title_zh":"[流言板]杜兰特快攻反击单臂暴扣连拿5分，目前个人已砍下21分5板5助"},{"site_id":"tophub","site_name":"TopHub","source":"虎扑社区 · NBA论坛热帖","title":"[流言板]韦德：莫布利可以多看看波什录像，他当年完美适配双核心","url":"https://bbs.hupu.com/637888460.html","published_at":null,"first_seen_at":"2026-03-14T02:28:43.039445Z","title_en":null,"title_zh":"[流言板]韦德：莫布利可以多看看波什录像，他当年完美适配双核心"},{"site_id":"tophub","site_name":"TopHub","source":"虎扑社区 · NBA论坛热帖","title":"[流言板]格林：连续输给摆烂球队很沮丧，我们必须想办法挺过去","url":"https://bbs.hupu.com/637888428.html","published_at":null,"first_seen_at":"2026-03-14T02:28:43.039445Z","title_en":null,"title_zh":"[流言板]格林：连续输给摆烂球队很沮丧，我们必须想办法挺过去"},{"site_id":"tophub","site_name":"TopHub","source":"虎扑社区 · NBA论坛热帖","title":"19年的伦纳德是杜兰特梦中的自己 你说选谁","url":"https://bbs.hupu.com/637888757.html","published_at":null,"first_seen_at":"2026-03-14T02:28:43.039445Z","title_en":null,"title_zh":"19年的伦纳德是杜兰特梦中的自己 你说选谁"},{"site_id":"tophub","site_name":"TopHub","source":"虎扑社区 · NBA论坛热帖","title":"格林杀疯了，球球顶着着猛龙硬解。再看看申京","url":"https://bbs.hupu.com/637890009.html","published_at":null,"first_seen_at":"2026-03-14T02:28:43.039445Z","title_en":null,"title_zh":"格林杀疯了，球球顶着着猛龙硬解。再看看申京"},{"site_id":"tophub","site_name":"TopHub","source":"虎扑社区 · NBA论坛热帖","title":"论实力肯定伦纳德，不过他出勤率太低了，所以我选kd","url":"https://bbs.hupu.com/637888392.html","published_at":null,"first_seen_at":"2026-03-14T02:28:43.039445Z","title_en":null,"title_zh":"论实力肯定伦纳德，不过他出勤率太低了，所以我选kd"},{"site_id":"tophub","site_name":"TopHub","source":"虎扑社区 · NBA论坛热帖","title":"[流言板]卢谈防守端进步：我们速度更快了，各方面都进步很大","url":"https://bbs.hupu.com/637889998.html","published_at":null,"first_seen_at":"2026-03-14T02:28:43.039445Z","title_en":null,"title_zh":"[流言板]卢谈防守端进步：我们速度更快了，各方面都进步很大"},{"site_id":"tophub","site_name":"TopHub","source":"虎扑社区 · NBA论坛热帖","title":"格林真是好起来了，这突破能力太让人羡慕了","url":"https://bbs.hupu.com/637888614.html","published_at":null,"first_seen_at":"2026-03-14T02:28:43.039445Z","title_en":null,"title_zh":"格林真是好起来了，这突破能力太让人羡慕了"},{"site_id":"tophub","site_name":"TopHub","source":"虎扑社区 · NBA论坛热帖","title":"风雪哥一次次神级表现，都是在敲打箭区脆弱的心灵","url":"https://bbs.hupu.com/637890130.html","published_at":null,"first_seen_at":"2026-03-14T02:28:43.039445Z","title_en":null,"title_zh":"风雪哥一次次神级表现，都是在敲打箭区脆弱的心灵"},{"site_id":"tophub","site_name":"TopHub","source":"懂球帝 · 今日头条","title":"广西恒宸新赛季将在南宁和钦州双城作战，赛季套票418元","url":"https://www.dongqiudi.com/article/5714849","published_at":null,"first_seen_at":"2026-03-14T02:28:43.039445Z","title_en":null,"title_zh":"广西恒宸新赛季将在南宁和钦州双城作战，赛季套票418元"},{"site_id":"tophub","site_name":"TopHub","source":"懂球帝 · 今日头条","title":"科尔谈阿德巴约砍83分：克莱14个三分纪录的最后一个也三连铁","url":"https://www.dongqiudi.com/article/5714836","published_at":null,"first_seen_at":"2026-03-14T02:28:43.039445Z","title_en":null,"title_zh":"科尔谈阿德巴约砍83分：克莱14个三分纪录的最后一个也三连铁"},{"site_id":"tophub","site_name":"TopHub","source":"懂球帝 · 今日头条","title":"刘建宏主持川超：上下齐心推动足球发展，希望谁都别松劲","url":"https://www.dongqiudi.com/article/5714844","published_at":null,"first_seen_at":"2026-03-14T02:28:43.039445Z","title_en":null,"title_zh":"刘建宏主持川超：上下齐心推动足球发展，希望谁都别松劲"},{"site_id":"tophub","site_name":"TopHub","source":"懂球帝 · 今日头条","title":"猛龙122-115逆转太阳，英格拉姆36分，格林34分，布克31分","url":"https://www.dongqiudi.com/article/5714837","published_at":null,"first_seen_at":"2026-03-14T02:28:43.039445Z","title_en":null,"title_zh":"猛龙122-115逆转太阳，英格拉姆36分，格林34分，布克31分"},{"site_id":"tophub","site_name":"TopHub","source":"懂球帝 · 今日头条","title":"官方：南京同曦签下美国后卫杰克逊-卡特莱特","url":"https://www.dongqiudi.com/article/5714829","published_at":null,"first_seen_at":"2026-03-14T02:28:43.039445Z","title_en":null,"title_zh":"官方：南京同曦签下美国后卫杰克逊-卡特莱特"},{"site_id":"tophub","site_name":"TopHub","source":"懂球帝 · 今日头条","title":"参加播客节目，索斯盖特晒出和弗兰克的合照：忙碌的几周","url":"https://www.dongqiudi.com/article/5714814","published_at":null,"first_seen_at":"2026-03-14T02:28:43.039445Z","title_en":null,"title_zh":"参加播客节目，索斯盖特晒出和弗兰克的合照：忙碌的几周"},{"site_id":"tophub","site_name":"TopHub","source":"懂球帝 · 今日头条","title":"国安观察丨第二轮就踢山东？关关难过关关过","url":"https://www.dongqiudi.com/article/5714381","published_at":null,"first_seen_at":"2026-03-14T02:28:43.039445Z","title_en":null,"title_zh":"国安观察丨第二轮就踢山东？关关难过关关过"},{"site_id":"tophub","site_name":"TopHub","source":"懂球帝 · 今日头条","title":"尼克斯101-92力克步行者，布伦森29分，米罗12+22","url":"https://www.dongqiudi.com/article/5714828","published_at":null,"first_seen_at":"2026-03-14T02:28:43.039445Z","title_en":null,"title_zh":"尼克斯101-92力克步行者，布伦森29分，米罗12+22"},{"site_id":"tophub","site_name":"TopHub","source":"懂球帝 · 今日头条","title":"格林：现在比赛节奏快应该缩短赛程，以前都是慢慢运球过半场","url":"https://www.dongqiudi.com/article/5714817","published_at":null,"first_seen_at":"2026-03-14T02:28:43.039445Z","title_en":null,"title_zh":"格林：现在比赛节奏快应该缩短赛程，以前都是慢慢运球过半场"},{"site_id":"tophub","site_name":"TopHub","source":"懂球帝 · 今日头条","title":"美媒：因美国未缴会费，WADA可能象征性禁止特朗普出席世界杯","url":"https://www.dongqiudi.com/article/5714813","published_at":null,"first_seen_at":"2026-03-14T02:28:43.039445Z","title_en":null,"title_zh":"美媒：因美国未缴会费，WADA可能象征性禁止特朗普出席世界杯"},{"site_id":"tophub","site_name":"TopHub","source":"懂球帝 · 今日头条","title":"骑士138-105大胜独行侠，莫布利15中12轰29+7，弗拉格25分","url":"https://www.dongqiudi.com/article/5714820","published_at":null,"first_seen_at":"2026-03-14T02:28:43.039445Z","title_en":null,"title_zh":"骑士138-105大胜独行侠，莫布利15中12轰29+7，弗拉格25分"},{"site_id":"tophub","site_name":"TopHub","source":"懂球帝 · 今日头条","title":"活塞126-110轻取灰熊，坎宁安17+8+15，杜伦15中12轰30+13","url":"https://www.dongqiudi.com/article/5714819","published_at":null,"first_seen_at":"2026-03-14T02:28:43.039445Z","title_en":null,"title_zh":"活塞126-110轻取灰熊，坎宁安17+8+15，杜伦15中12轰30+13"},{"site_id":"tophub","site_name":"TopHub","source":"懂球帝 · 今日头条","title":"马卡：哈维的言论不会影响拉波选票；丰特称引进哈兰德是骗局","url":"https://www.dongqiudi.com/article/5714808","published_at":null,"first_seen_at":"2026-03-14T02:28:43.039445Z","title_en":null,"title_zh":"马卡：哈维的言论不会影响拉波选票；丰特称引进哈兰德是骗局"},{"site_id":"tophub","site_name":"TopHub","source":"懂球帝 · 今日头条","title":"伊朗女足主帅：国家电视台针对球员的言论导致她们最终选择不回国","url":"https://www.dongqiudi.com/article/5714805","published_at":null,"first_seen_at":"2026-03-14T02:28:43.039445Z","title_en":null,"title_zh":"伊朗女足主帅：国家电视台针对球员的言论导致她们最终选择不回国"},{"site_id":"tophub","site_name":"TopHub","source":"懂球帝 · 今日头条","title":"阿德巴约：我不在计划里，不是他们推崇打破纪录的那种得分手","url":"https://www.dongqiudi.com/article/5714810","published_at":null,"first_seen_at":"2026-03-14T02:28:43.039445Z","title_en":null,"title_zh":"阿德巴约：我不在计划里，不是他们推崇打破纪录的那种得分手"},{"site_id":"tophub","site_name":"TopHub","source":"懂球帝 · 今日头条","title":"记者：巴萨主席候选人丰特想签哈兰德，已派代表与曼城会面","url":"https://www.dongqiudi.com/article/5711064","published_at":null,"first_seen_at":"2026-03-14T02:28:43.039445Z","title_en":null,"title_zh":"记者：巴萨主席候选人丰特想签哈兰德，已派代表与曼城会面"},{"site_id":"tophub","site_name":"TopHub","source":"懂球帝 · 今日头条","title":"都体：尤文考察估价3500万的基维奥尔，并视埃德松为中场首选","url":"https://www.dongqiudi.com/article/5714796","published_at":null,"first_seen_at":"2026-03-14T02:28:43.039445Z","title_en":null,"title_zh":"都体：尤文考察估价3500万的基维奥尔，并视埃德松为中场首选"},{"site_id":"tophub","site_name":"TopHub","source":"懂球帝 · 今日头条","title":"闪耀球员女友在观战欧冠期间遭本队球迷歧视，俱乐部发文声援","url":"https://www.dongqiudi.com/article/5714799","published_at":null,"first_seen_at":"2026-03-14T02:28:43.039445Z","title_en":null,"title_zh":"闪耀球员女友在观战欧冠期间遭本队球迷歧视，俱乐部发文声援"},{"site_id":"tophub","site_name":"TopHub","source":"懂球帝 · 今日头条","title":"希勒：对热刺完全失去信心，他们不可能在安菲尔德战胜利物浦","url":"https://www.dongqiudi.com/article/5714795","published_at":null,"first_seen_at":"2026-03-14T02:28:43.039445Z","title_en":null,"title_zh":"希勒：对热刺完全失去信心，他们不可能在安菲尔德战胜利物浦"},{"site_id":"iris","site_name":"Info Flow","source":"虎嗅 (Huxiu)","title":"对话腾讯“龙虾特攻队”：火爆的线下装机复盘以及如何守住安全红线？","url":"https://www.huxiu.com/article/4842014.html?f=rss","published_at":"2026-03-14T02:28:10Z","first_seen_at":"2026-03-14T04:23:14.307669Z","title_en":null,"title_zh":"对话腾讯“龙虾特攻队”：火爆的线下装机复盘以及如何守住安全红线？"},{"site_id":"iris","site_name":"Info Flow","source":"V2EX (创意工作者社区)","title":"[程序员] 大家公司怎么使用 ai 的?","url":"https://www.v2ex.com/t/1198216","published_at":"2026-03-14T02:28:04Z","first_seen_at":"2026-03-14T02:28:43.039445Z","title_en":null,"title_zh":"[程序员] 大家公司怎么使用 ai 的?"},{"site_id":"iris","site_name":"Info Flow","source":"IT之家 (ITHome)","title":"鸿蒙智行享界 S9T“星玫粉”新车色官宣，将携 S9 月绒白于北京时装周正式发布","url":"https://www.ithome.com/0/929/016.htm","published_at":"2026-03-14T02:27:25Z","first_seen_at":"2026-03-14T04:23:14.307669Z","title_en":null,"title_zh":"鸿蒙智行享界 S9T“星玫粉”新车色官宣，将携 S9 月绒白于北京时装周正式发布"},{"site_id":"iris","site_name":"Info Flow","source":"IT之家 (ITHome)","title":"鸿蒙智行享界 S9T“星莓粉”官宣，北京时装周发布","url":"https://www.ithome.com/0/929/016.htm","published_at":"2026-03-14T02:27:25Z","first_seen_at":"2026-03-14T02:28:43.039445Z","title_en":null,"title_zh":"鸿蒙智行享界 S9T“星莓粉”官宣，北京时装周发布"},{"site_id":"techurls","site_name":"TechURLs","source":"Hacker News","title":"Optimizing Content for Agents","url":"https://cra.mr/optimizing-content-for-agents","published_at":"2026-03-14T02:27:00Z","first_seen_at":"2026-03-14T04:23:14.307669Z","title_en":"Optimizing Content for Agents","title_zh":"为代理商优化内容"},{"site_id":"iris","site_name":"Info Flow","source":"IT之家 (ITHome)","title":"卡色 150mm f/5.6 全画幅自动对焦折返镜头发布：3850 元，适配佳能 EF / 索尼 E 卡口","url":"https://www.ithome.com/0/929/015.htm","published_at":"2026-03-14T02:25:14Z","first_seen_at":"2026-03-14T02:28:43.039445Z","title_en":null,"title_zh":"卡色 150mm f/5.6 全画幅自动对焦折返镜头发布：3850 元，适配佳能 EF / 索尼 E 卡口"},{"site_id":"iris","site_name":"Info Flow","source":"IT之家 (ITHome)","title":"余承东谈华为全场景生态，已经进入全链生态时代","url":"https://www.ithome.com/0/929/014.htm","published_at":"2026-03-14T02:24:09Z","first_seen_at":"2026-03-14T02:28:43.039445Z","title_en":null,"title_zh":"余承东谈华为全场景生态，已经进入全链生态时代"},{"site_id":"iris","site_name":"Info Flow","source":"IT之家 (ITHome)","title":"AMD 优化 RDNA 5 显卡核心指令，部分场景性能可近乎翻倍","url":"https://www.ithome.com/0/929/013.htm","published_at":"2026-03-14T02:23:50Z","first_seen_at":"2026-03-14T02:28:43.039445Z","title_en":null,"title_zh":"AMD 优化 RDNA 5 显卡核心指令，部分场景性能可近乎翻倍"},{"site_id":"iris","site_name":"Info Flow","source":"IT之家 (ITHome)","title":"鸿蒙智行问界 M6 内饰图公布：紫慕白双拼，“会转头”的随动屏 + 灵感橱窗","url":"https://www.ithome.com/0/929/012.htm","published_at":"2026-03-14T02:18:52Z","first_seen_at":"2026-03-14T02:28:43.039445Z","title_en":null,"title_zh":"鸿蒙智行问界 M6 内饰图公布：紫慕白双拼，“会转头”的随动屏 + 灵感橱窗"},{"site_id":"buzzing","site_name":"Buzzing","source":"www.nature.com","title":"中国高层重申目标：力争成为科技和人工智能领域的全球领导者","url":"https://www.nature.com/articles/d41586-026-00814-3","published_at":"2026-03-14T02:16:42.277000Z","first_seen_at":"2026-03-14T02:28:43.039445Z","title_en":null,"title_zh":"中国高层重申目标：力争成为科技和人工智能领域的全球领导者"},{"site_id":"buzzing","site_name":"Buzzing","source":"www.reuters.com","title":"中国敦促阿富汗和巴基斯坦通过对话而非武力化解紧张局势","url":"https://www.reuters.com/world/china/china-urges-afghanistan-pakistan-resolve-tensions-via-talks-not-force-2026-03-14","published_at":"2026-03-14T02:16:42.273000Z","first_seen_at":"2026-03-14T02:28:43.039445Z","title_en":null,"title_zh":"中国敦促阿富汗和巴基斯坦通过对话而非武力化解紧张局势"},{"site_id":"buzzing","site_name":"Buzzing","source":"www.reuters.com","title":"美国男足国家队球员詹姆斯·桑兹（脚踝手术）能否出战世界杯尚不确定","url":"https://www.reuters.com/sports/soccer/usmnts-james-sands-ankle-surgery-doubt-world-cup--flm-2026-03-14","published_at":"2026-03-14T02:16:42.270000Z","first_seen_at":"2026-03-14T02:28:43.039445Z","title_en":null,"title_zh":"美国男足国家队球员詹姆斯·桑兹（脚踝手术）能否出战世界杯尚不确定"},{"site_id":"buzzing","site_name":"Buzzing","source":"dlvr.it","title":"8名被指控与“反法西斯运动”有联系的人员因在得克萨斯州一处移民设施发生枪击事件，被以恐怖主义罪名判处有罪","url":"http://dlvr.it/TRTc9V","published_at":"2026-03-14T02:16:42.173000Z","first_seen_at":"2026-03-14T02:28:43.039445Z","title_en":null,"title_zh":"8名被指控与“反法西斯运动”有联系的人员因在得克萨斯州一处移民设施发生枪击事件，被以恐怖主义罪名判处有罪"},{"site_id":"buzzing","site_name":"Buzzing","source":"reut.rs","title":"《华尔街日报》报道称，特朗普政府将因促成TikTok交易获得100亿美元佣金","url":"https://reut.rs/4sH6x3j","published_at":"2026-03-14T02:16:42.170000Z","first_seen_at":"2026-03-14T02:28:43.039445Z","title_en":null,"title_zh":"《华尔街日报》报道称，特朗普政府将因促成TikTok交易获得100亿美元佣金"},{"site_id":"buzzing","site_name":"Buzzing","source":"finance.yahoo.com","title":"尼德姆将库珀公司（COO）的目标股价从99美元上调至101美元，并维持“买入”评级","url":"https://finance.yahoo.com/news/needham-raises-price-target-cooper-204251145.html","published_at":"2026-03-14T02:16:42.166000Z","first_seen_at":"2026-03-14T02:28:43.039445Z","title_en":null,"title_zh":"尼德姆将库珀公司（COO）的目标股价从99美元上调至101美元，并维持“买入”评级"},{"site_id":"buzzing","site_name":"Buzzing","source":"finance.yahoo.com","title":"Alliance Laundry Holdings Inc. 2025年第四季度财报电话会议摘要","url":"https://finance.yahoo.com/news/alliance-laundry-holdings-inc-q4-204152122.html","published_at":"2026-03-14T02:16:42.162000Z","first_seen_at":"2026-03-14T02:28:43.039445Z","title_en":null,"title_zh":"Alliance Laundry Holdings Inc. 2025年第四季度财报电话会议摘要"},{"site_id":"buzzing","site_name":"Buzzing","source":"finance.yahoo.com","title":"Here Group Limited 2026年第二季度财报电话会议摘要","url":"https://finance.yahoo.com/news/group-limited-q2-2026-earnings-204114086.html","published_at":"2026-03-14T02:16:42.159000Z","first_seen_at":"2026-03-14T02:28:43.039445Z","title_en":null,"title_zh":"Here Group Limited 2026年第二季度财报电话会议摘要"},{"site_id":"buzzing","site_name":"Buzzing","source":"finance.yahoo.com","title":"Saga Communications, Inc. 2025年第四季度财报电话会议摘要","url":"https://finance.yahoo.com/news/saga-communications-inc-q4-2025-204018225.html","published_at":"2026-03-14T02:16:42.155000Z","first_seen_at":"2026-03-14T02:28:43.039445Z","title_en":null,"title_zh":"Saga Communications, Inc. 2025年第四季度财报电话会议摘要"},{"site_id":"buzzing","site_name":"Buzzing","source":"finance.yahoo.com","title":"分析师称，美国放宽出口限制及释放战略储备并不能缓解加油站的油价压力","url":"https://finance.yahoo.com/news/us-shipping-waiver-release-stockpiles-203903387.html","published_at":"2026-03-14T02:16:42.153000Z","first_seen_at":"2026-03-14T02:28:43.039445Z","title_en":null,"title_zh":"分析师称，美国放宽出口限制及释放战略储备并不能缓解加油站的油价压力"},{"site_id":"buzzing","site_name":"Buzzing","source":"finance.yahoo.com","title":"受伊朗战争和信贷危机影响，股市暴跌","url":"https://finance.yahoo.com/news/stocks-slump-iran-war-credit-203540448.html","published_at":"2026-03-14T02:16:42.149000Z","first_seen_at":"2026-03-14T02:28:43.039445Z","title_en":null,"title_zh":"受伊朗战争和信贷危机影响，股市暴跌"},{"site_id":"buzzing","site_name":"Buzzing","source":"finance.yahoo.com","title":"全球战略石油储备（下）：霍尔木兹海峡的“崩溃天数”","url":"https://finance.yahoo.com/news/global-strategic-petroleum-reserves-part-203056310.html","published_at":"2026-03-14T02:16:42.145000Z","first_seen_at":"2026-03-14T02:28:43.039445Z","title_en":null,"title_zh":"全球战略石油储备（下）：霍尔木兹海峡的“崩溃天数”"},{"site_id":"buzzing","site_name":"Buzzing","source":"finance.yahoo.com","title":"华特迪士尼公司（DIS）旗下皮克斯新片在美国首映表现强劲","url":"https://finance.yahoo.com/news/walt-disney-company-dis-sees-203045807.html","published_at":"2026-03-14T02:16:42.142000Z","first_seen_at":"2026-03-14T02:28:43.039445Z","title_en":null,"title_zh":"华特迪士尼公司（DIS）旗下皮克斯新片在美国首映表现强劲"},{"site_id":"buzzing","site_name":"Buzzing","source":"finance.yahoo.com","title":"BMO认为，在动荡的零售行业中，好市多批发公司（COST）是一项稳健的投资选择","url":"https://finance.yahoo.com/news/bmo-sees-costco-wholesale-corporation-202948824.html","published_at":"2026-03-14T02:16:42.138000Z","first_seen_at":"2026-03-14T02:28:43.039445Z","title_en":null,"title_zh":"BMO认为，在动荡的零售行业中，好市多批发公司（COST）是一项稳健的投资选择"},{"site_id":"buzzing","site_name":"Buzzing","source":"finance.yahoo.com","title":"美银指出TJX公司（TJX）盈利能力和销售业绩表现强劲","url":"https://finance.yahoo.com/news/bofa-notes-strong-profitability-sales-202850405.html","published_at":"2026-03-14T02:16:42.135000Z","first_seen_at":"2026-03-14T02:28:43.039445Z","title_en":null,"title_zh":"美银指出TJX公司（TJX）盈利能力和销售业绩表现强劲"},{"site_id":"buzzing","site_name":"Buzzing","source":"finance.yahoo.com","title":"尽管Dollar General Corporation (DG) 交出了强劲的季度业绩，Piper Sandler 仍维持对其“中性”评级","url":"https://finance.yahoo.com/news/piper-sandler-maintains-neutral-view-202758166.html","published_at":"2026-03-14T02:16:42.131000Z","first_seen_at":"2026-03-14T02:28:43.039445Z","title_en":null,"title_zh":"尽管Dollar General Corporation (DG) 交出了强劲的季度业绩，Piper Sandler 仍维持对其“中性”评级"},{"site_id":"buzzing","site_name":"Buzzing","source":"finance.yahoo.com","title":"美银上调维多利亚的秘密公司（VSCO）至2027年的每股收益预期","url":"https://finance.yahoo.com/news/bofa-lifts-eps-forecasts-victoria-202719367.html","published_at":"2026-03-14T02:16:42.128000Z","first_seen_at":"2026-03-14T02:28:43.039445Z","title_en":null,"title_zh":"美银上调维多利亚的秘密公司（VSCO）至2027年的每股收益预期"},{"site_id":"buzzing","site_name":"Buzzing","source":"finance.yahoo.com","title":"Saga Communications第四季度财报电话会议要点","url":"https://finance.yahoo.com/news/saga-communications-q4-earnings-call-202704931.html","published_at":"2026-03-14T02:16:42.124000Z","first_seen_at":"2026-03-14T02:28:43.039445Z","title_en":null,"title_zh":"Saga Communications第四季度财报电话会议要点"},{"site_id":"buzzing","site_name":"Buzzing","source":"finance.yahoo.com","title":"Alliance Laundry第四季度财报电话会议要点","url":"https://finance.yahoo.com/news/alliance-laundry-q4-earnings-call-202704866.html","published_at":"2026-03-14T02:16:42.120000Z","first_seen_at":"2026-03-14T02:28:43.039445Z","title_en":null,"title_zh":"Alliance Laundry第四季度财报电话会议要点"},{"site_id":"buzzing","site_name":"Buzzing","source":"finance.yahoo.com","title":"Build-A-Bear Workshop 第四季度财报电话会议要点","url":"https://finance.yahoo.com/news/build-bear-workshop-q4-earnings-202704293.html","published_at":"2026-03-14T02:16:42.117000Z","first_seen_at":"2026-03-14T02:28:43.039445Z","title_en":null,"title_zh":"Build-A-Bear Workshop 第四季度财报电话会议要点"},{"site_id":"buzzing","site_name":"Buzzing","source":"www.barrons.com","title":"这只铜股值得关注。铜价正迎来一波上涨行情。","url":"https://www.barrons.com/articles/copper-stock-freeport-mcmoran-worth-mining-metals-boom-98e6ef5e?siteid=yhoof2&yptr=yahoo","published_at":"2026-03-14T02:16:42.113000Z","first_seen_at":"2026-03-14T02:28:43.039445Z","title_en":null,"title_zh":"这只铜股值得关注。铜价正迎来一波上涨行情。"},{"site_id":"buzzing","site_name":"Buzzing","source":"finance.yahoo.com","title":"随着销售势头增强，BMO上调了Casey’s General Stores（CASY）的估值","url":"https://finance.yahoo.com/news/bmo-adjusts-casey-general-stores-202640571.html","published_at":"2026-03-14T02:16:42.110000Z","first_seen_at":"2026-03-14T02:28:43.039445Z","title_en":null,"title_zh":"随着销售势头增强，BMO上调了Casey’s General Stores（CASY）的估值"},{"site_id":"buzzing","site_name":"Buzzing","source":"finance.yahoo.com","title":"花旗预计威廉姆斯-索诺玛公司（WSM）第四季度业绩将超出市场预期","url":"https://finance.yahoo.com/news/citi-expects-williams-sonoma-inc-202538221.html","published_at":"2026-03-14T02:16:42.106000Z","first_seen_at":"2026-03-14T02:28:43.039445Z","title_en":null,"title_zh":"花旗预计威廉姆斯-索诺玛公司（WSM）第四季度业绩将超出市场预期"},{"site_id":"buzzing","site_name":"Buzzing","source":"finance.yahoo.com","title":"Truist 指出 Toll Brothers, Inc. (TOL) 估值具有吸引力","url":"https://finance.yahoo.com/news/truist-highlights-attractive-valuation-toll-202453347.html","published_at":"2026-03-14T02:16:42.103000Z","first_seen_at":"2026-03-14T02:28:43.039445Z","title_en":null,"title_zh":"Truist 指出 Toll Brothers, Inc. (TOL) 估值具有吸引力"},{"site_id":"buzzing","site_name":"Buzzing","source":"finance.yahoo.com","title":"奥本海默认为，伦诺克斯国际公司（LII）的2030年财务目标切实可行","url":"https://finance.yahoo.com/news/oppenheimer-sees-achievable-2030-financial-202409176.html","published_at":"2026-03-14T02:16:42.099000Z","first_seen_at":"2026-03-14T02:28:43.039445Z","title_en":null,"title_zh":"奥本海默认为，伦诺克斯国际公司（LII）的2030年财务目标切实可行"},{"site_id":"buzzing","site_name":"Buzzing","source":"finance.yahoo.com","title":"TopBuild Corp. (BLD) 宣布第四季度营收增长13%，得益于收购业务","url":"https://finance.yahoo.com/news/topbuild-corp-bld-reports-13-202327368.html","published_at":"2026-03-14T02:16:42.096000Z","first_seen_at":"2026-03-14T02:28:43.039445Z","title_en":null,"title_zh":"TopBuild Corp. (BLD) 宣布第四季度营收增长13%，得益于收购业务"},{"site_id":"buzzing","site_name":"Buzzing","source":"finance.yahoo.com","title":"RBC指出，房地产市场疲软是Installed Building Products, Inc.（IBP）面临的风险","url":"https://finance.yahoo.com/news/rbc-flags-housing-market-weakness-202229113.html","published_at":"2026-03-14T02:16:42.092000Z","first_seen_at":"2026-03-14T02:28:43.039445Z","title_en":null,"title_zh":"RBC指出，房地产市场疲软是Installed Building Products, Inc.（IBP）面临的风险"},{"site_id":"buzzing","site_name":"Buzzing","source":"finance.yahoo.com","title":"库吉诺欣赏Meta的成本管控能力：在AI支出方面“清楚界限所在”","url":"https://finance.yahoo.com/news/cuggino-likes-meta-cost-discipline-202154244.html","published_at":"2026-03-14T02:16:42.088000Z","first_seen_at":"2026-03-14T02:28:43.039445Z","title_en":null,"title_zh":"库吉诺欣赏Meta的成本管控能力：在AI支出方面“清楚界限所在”"},{"site_id":"buzzing","site_name":"Buzzing","source":"finance.yahoo.com","title":"链接：Netflix在未达成华纳兄弟探索公司交易的情况下，故事线更为简单","url":"https://finance.yahoo.com/news/netflix-simpler-story-without-warner-202116907.html","published_at":"2026-03-14T02:16:42.085000Z","first_seen_at":"2026-03-14T02:28:43.039445Z","title_en":null,"title_zh":"链接：Netflix在未达成华纳兄弟探索公司交易的情况下，故事线更为简单"},{"site_id":"buzzing","site_name":"Buzzing","source":"news.google.com","title":"道琼斯期货：油价与伊朗战事拖累股市下行；英伟达GTC大会及美光财报即将发布 - Investor's Business Daily","url":"https://news.google.com/rss/articles/CBMiwAFBVV95cUxNbFdhTjVtelZ1alNONWtuamZzZi1qSm9laHhRRmdBbWdidUlCVWs3al93N21vYVNnSGVHLXpWYjV2YnIzVzlaMFkyV2RJb2hleC1Xanc5M0sydjRyQ2ZCNFZPTlBwdmwzR183TkZpY0FabExKME5VM2hmdDB6bUxJRE4zUklsYkdwT0w1RFZYLWlIUS1kek1oWGIyYS1OTEcwOUZkT3ZpVXR1a2xqR3FpcExTajFnd2RCZ0twRzNBOVU?oc=5&hl=en-US&gl=US&ceid=US%3Aen","published_at":"2026-03-14T02:16:42.030000Z","first_seen_at":"2026-03-14T02:28:43.039445Z","title_en":null,"title_zh":"道琼斯期货：油价与伊朗战事拖累股市下行；英伟达GTC大会及美光财报即将发布 - Investor's Business Daily"}]}